Products.CMFEditions-4.0.6-py3.13-nspkg.pth
Products/CMFEditions/ArchivistTool.py
Products/CMFEditions/CopyModifyMergeRepositoryTool.py
Products/CMFEditions/KeepLastNVersionsTool.py
Products/CMFEditions/ModifierRegistryTool.py
Products/CMFEditions/Modifiers.py
Products/CMFEditions/Permissions.py
Products/CMFEditions/ReferenceFactoriesTool.py
Products/CMFEditions/StandardModifiers.py
Products/CMFEditions/UniqueIdHandlerTool.py
Products/CMFEditions/VersionPolicies.py
Products/CMFEditions/ZVCStorageTool.py
Products/CMFEditions/__init__.py
Products/CMFEditions/configure.zcml
Products/CMFEditions/historyidhandlertool.py
Products/CMFEditions/permissions.zcml
Products/CMFEditions/profiles.zcml
Products/CMFEditions/setuphandlers.py
Products/CMFEditions/subscriber.py
Products/CMFEditions/testing.py
Products/CMFEditions/tool.gif
Products/CMFEditions/utilities.py
Products/CMFEditions/browser/__init__.py
Products/CMFEditions/browser/compare.css
Products/CMFEditions/browser/configure.zcml
Products/CMFEditions/browser/diff.py
Products/CMFEditions/browser/policies.py
Products/CMFEditions/browser/utils.py
Products/CMFEditions/browser/views.py
Products/CMFEditions/browser/templates/diff.pt
Products/CMFEditions/browser/templates/diff_legend.pt
Products/CMFEditions/browser/templates/version_file_view.pt
Products/CMFEditions/browser/templates/version_image_view.pt
Products/CMFEditions/browser/templates/version_metadata_view.pt
Products/CMFEditions/browser/templates/versions_history_form.pt
Products/CMFEditions/exportimport/__init__.py
Products/CMFEditions/exportimport/configure.zcml
Products/CMFEditions/exportimport/repository.py
Products/CMFEditions/interfaces/IArchivist.py
Products/CMFEditions/interfaces/IModifier.py
Products/CMFEditions/interfaces/IPurgePolicy.py
Products/CMFEditions/interfaces/IReferenceFactories.py
Products/CMFEditions/interfaces/IRepository.py
Products/CMFEditions/interfaces/IStorage.py
Products/CMFEditions/interfaces/IVersionPolicy.py
products_cmfeditions-4.0.6.dist-info/METADATA
products_cmfeditions-4.0.6.dist-info/WHEEL
products_cmfeditions-4.0.6.dist-info/entry_points.txt
products_cmfeditions-4.0.6.dist-info/namespace_packages.txt
products_cmfeditions-4.0.6.dist-info/top_level.txt
products_cmfeditions-4.0.6.dist-info/RECORD
