Metadata-Version: 2.4
Name: Products.CMFEditions
Version: 4.0.6
Summary: Versioning for Plone
Home-page: https://pypi.org/project/Products.CMFEditions
Author: CMFEditions contributors
Author-email: collective-versioning@lists.sourceforge.net
License: GPL
Keywords: Versioning Plone
Classifier: Development Status :: 5 - Production/Stable
Classifier: Environment :: Web Environment
Classifier: Framework :: Plone
Classifier: Framework :: Plone :: 6.0
Classifier: Framework :: Plone :: Core
Classifier: Framework :: Zope :: 5
Classifier: License :: OSI Approved :: GNU General Public License v2 (GPLv2)
Classifier: Operating System :: OS Independent
Classifier: Programming Language :: Python
Classifier: Programming Language :: Python :: 3.8
Classifier: Programming Language :: Python :: 3.9
Classifier: Programming Language :: Python :: 3.10
Classifier: Programming Language :: Python :: 3.11
Requires-Python: >=3.8
Requires-Dist: BTrees
Requires-Dist: Missing
Requires-Dist: Persistence
Requires-Dist: Products.CMFCore>=2.1
Requires-Dist: Products.CMFDiffTool
Requires-Dist: Products.CMFUid
Requires-Dist: Products.GenericSetup>=1.4.0
Requires-Dist: Products.ZopeVersionControl
Requires-Dist: Products.statusmessages
Requires-Dist: Zope>=5
Requires-Dist: plone.folder
Requires-Dist: plone.locking
Requires-Dist: setuptools
Requires-Dist: zope.copy
Requires-Dist: zope.dottedname
Provides-Extra: test
Requires-Dist: plone.app.contenttypes[test]; extra == "test"
Requires-Dist: plone.app.testing; extra == "test"
Requires-Dist: plone.app.textfield; extra == "test"
Requires-Dist: plone.base; extra == "test"
Requires-Dist: plone.namedfile; extra == "test"
Dynamic: author
Dynamic: author-email
Dynamic: classifier
Dynamic: description
Dynamic: description-content-type
Dynamic: home-page
Dynamic: keywords
Dynamic: license
Dynamic: provides-extra
Dynamic: requires-dist
Dynamic: requires-python
Dynamic: summary
